{
    "shapes": [
        {
            "label": "1",
            "line_color": null,
            "fill_color": null,
            "points": [
                [
                    550,
                    112
                ],
                [
                    530,
                    70
                ],
                [
                    435,
                    113
                ],
                [
                    340,
                    166
                ],
                [
                    361,
                    204
                ]
            ]
        },
        {
            "label": "1",
            "line_color": null,
            "fill_color": null,
            "points": [
                [
                    583,
                    181
                ],
                [
                    620,
                    159
                ],
                [
                    685,
                    263
                ],
                [
                    649,
                    285
                ]
            ]
        },
        {
            "label": "1",
            "line_color": null,
            "fill_color": null,
            "points": [
                [
                    104,
                    459
                ],
                [
                    140,
                    436
                ],
                [
                    271,
                    645
                ],
                [
                    233,
                    670
                ]
            ]
        },
        {
            "label": "1",
            "line_color": null,
            "fill_color": null,
            "points": [
                [
                    175,
                    414
                ],
                [
                    139,
                    436
                ],
                [
                    136,
                    438
                ],
                [
                    258,
                    630
                ],
                [
                    294,
                    608
                ],
                [
                    295,
                    605
                ]
            ]
        },
        {
            "label": "1",
            "line_color": null,
            "fill_color": null,
            "points": [
                [
                    308,
                    549
                ],
                [
                    346,
                    525
                ],
                [
                    239,
                    352
                ],
                [
                    200,
                    377
                ]
            ]
        },
        {
            "label": "1",
            "line_color": null,
            "fill_color": null,
            "points": [
                [
                    274,
                    329
                ],
                [
                    236,
                    354
                ],
                [
                    334,
                    510
                ],
                [
                    372,
                    485
                ]
            ]
        },
        {
            "label": "1",
            "line_color": null,
            "fill_color": null,
            "points": [
                [
                    534,
                    188
                ],
                [
                    499,
                    211
                ],
                [
                    575,
                    333
                ],
                [
                    613,
                    307
                ]
            ]
        },
        {
            "label": "1",
            "line_color": null,
            "fill_color": null,
            "points": [
                [
                    463,
                    234
                ],
                [
                    500,
                    210
                ],
                [
                    577,
                    331
                ],
                [
                    541,
                    355
                ]
            ]
        },
        {
            "label": "1",
            "line_color": null,
            "fill_color": null,
            "points": [
                [
                    418,
                    241
                ],
                [
                    384,
                    261
                ],
                [
                    383,
                    262
                ],
                [
                    466,
                    399
                ],
                [
                    503,
                    376
                ]
            ]
        },
        {
            "label": "1",
            "line_color": null,
            "fill_color": null,
            "points": [
                [
                    309,
                    308
                ],
                [
                    347,
                    285
                ],
                [
                    434,
                    421
                ],
                [
                    399,
                    445
                ]
            ]
        },
        {
            "label": "1",
            "line_color": null,
            "fill_color": null,
            "points": [
                [
                    307,
                    235
                ],
                [
                    284,
                    198
                ],
                [
                    152,
                    288
                ],
                [
                    62,
                    358
                ],
                [
                    32,
                    385
                ],
                [
                    29,
                    388
                ],
                [
                    57,
                    419
                ],
                [
                    65,
                    418
                ],
                [
                    79,
                    403
                ],
                [
                    76,
                    398
                ],
                [
                    106,
                    378
                ],
                [
                    178,
                    323
                ]
            ]
        }
    ],
    "lineColor": [
        0,
        255,
        0,
        128
    ],
    "fillColor": [
        255,
        0,
        0,
        128
    ]
}