{
    "shapes": [
        {
            "label": "1",
            "line_color": null,
            "fill_color": null,
            "points": [
                [
                    79,
                    56
                ],
                [
                    16,
                    45
                ],
                [
                    0,
                    145
                ],
                [
                    64,
                    157
                ]
            ]
        },
        {
            "label": "1",
            "line_color": null,
            "fill_color": null,
            "points": [
                [
                    160,
                    16
                ],
                [
                    219,
                    34
                ],
                [
                    195,
                    162
                ],
                [
                    133,
                    152
                ]
            ]
        }
    ],
    "lineColor": [
        0,
        255,
        0,
        128
    ],
    "fillColor": [
        255,
        0,
        0,
        128
    ]
}