{
    "shapes": [
        {
            "label": "1",
            "line_color": null,
            "fill_color": null,
            "points": [
                [
                    570,
                    1267
                ],
                [
                    625,
                    1266
                ],
                [
                    625,
                    1055
                ],
                [
                    572,
                    1055
                ]
            ]
        },
        {
            "label": "1",
            "line_color": null,
            "fill_color": null,
            "points": [
                [
                    577,
                    821
                ],
                [
                    629,
                    832
                ],
                [
                    627,
                    859
                ],
                [
                    623,
                    893
                ],
                [
                    624,
                    955
                ],
                [
                    624,
                    1030
                ],
                [
                    572,
                    1030
                ],
                [
                    571,
                    954
                ],
                [
                    571,
                    892
                ],
                [
                    573,
                    849
                ]
            ]
        },
        {
            "label": "1",
            "line_color": null,
            "fill_color": null,
            "points": [
                [
                    588,
                    782
                ],
                [
                    638,
                    801
                ],
                [
                    630,
                    828
                ],
                [
                    580,
                    812
                ]
            ]
        },
        {
            "label": "1",
            "line_color": null,
            "fill_color": null,
            "points": [
                [
                    604,
                    748
                ],
                [
                    650,
                    771
                ],
                [
                    640,
                    795
                ],
                [
                    591,
                    777
                ]
            ]
        },
        {
            "label": "1",
            "line_color": null,
            "fill_color": null,
            "points": [
                [
                    1614,
                    563
                ],
                [
                    1614,
                    618
                ],
                [
                    1631,
                    618
                ],
                [
                    1629,
                    607
                ],
                [
                    1632,
                    594
                ],
                [
                    1638,
                    593
                ],
                [
                    1642,
                    591
                ],
                [
                    1642,
                    563
                ]
            ]
        },
        {
            "label": "1",
            "line_color": null,
            "fill_color": null,
            "points": [
                [
                    1604,
                    563
                ],
                [
                    1604,
                    618
                ],
                [
                    1554,
                    618
                ],
                [
                    1553,
                    563
                ]
            ]
        },
        {
            "label": "1",
            "line_color": null,
            "fill_color": null,
            "points": [
                [
                    1542,
                    564
                ],
                [
                    1543,
                    617
                ],
                [
                    1492,
                    618
                ],
                [
                    1491,
                    564
                ]
            ]
        },
        {
            "label": "1",
            "line_color": null,
            "fill_color": null,
            "points": [
                [
                    1481,
                    563
                ],
                [
                    1481,
                    619
                ],
                [
                    1431,
                    618
                ],
                [
                    1429,
                    562
                ]
            ]
        },
        {
            "label": "1",
            "line_color": null,
            "fill_color": null,
            "points": [
                [
                    1555,
                    505
                ],
                [
                    1555,
                    451
                ],
                [
                    901,
                    449
                ],
                [
                    835,
                    454
                ],
                [
                    789,
                    463
                ],
                [
                    758,
                    471
                ],
                [
                    734,
                    481
                ],
                [
                    753,
                    532
                ],
                [
                    781,
                    521
                ],
                [
                    827,
                    510
                ],
                [
                    873,
                    505
                ],
                [
                    921,
                    504
                ]
            ]
        },
        {
            "label": "1",
            "line_color": null,
            "fill_color": null,
            "points": [
                [
                    1556,
                    332
                ],
                [
                    1554,
                    390
                ],
                [
                    1307,
                    389
                ],
                [
                    936,
                    389
                ],
                [
                    860,
                    390
                ],
                [
                    822,
                    394
                ],
                [
                    777,
                    404
                ],
                [
                    760,
                    352
                ],
                [
                    814,
                    341
                ],
                [
                    870,
                    337
                ],
                [
                    1087,
                    337
                ],
                [
                    1527,
                    337
                ]
            ]
        },
        {
            "label": "1",
            "line_color": null,
            "fill_color": null,
            "points": [
                [
                    1555,
                    274
                ],
                [
                    1555,
                    222
                ],
                [
                    1427,
                    222
                ],
                [
                    868,
                    222
                ],
                [
                    816,
                    226
                ],
                [
                    763,
                    234
                ],
                [
                    734,
                    241
                ],
                [
                    730,
                    245
                ],
                [
                    718,
                    245
                ],
                [
                    714,
                    245
                ],
                [
                    714,
                    257
                ],
                [
                    727,
                    295
                ],
                [
                    752,
                    292
                ],
                [
                    799,
                    283
                ],
                [
                    847,
                    278
                ],
                [
                    944,
                    277
                ]
            ]
        },
        {
            "label": "1",
            "line_color": null,
            "fill_color": null,
            "points": [
                [
                    654,
                    323
                ],
                [
                    631,
                    274
                ],
                [
                    558,
                    313
                ],
                [
                    581,
                    359
                ],
                [
                    606,
                    349
                ]
            ]
        },
        {
            "label": "1",
            "line_color": null,
            "fill_color": null,
            "points": [
                [
                    1641,
                    48
                ],
                [
                    1641,
                    0
                ],
                [
                    787,
                    0
                ],
                [
                    711,
                    12
                ],
                [
                    637,
                    31
                ],
                [
                    563,
                    55
                ],
                [
                    492,
                    89
                ],
                [
                    428,
                    122
                ],
                [
                    454,
                    168
                ],
                [
                    479,
                    158
                ],
                [
                    542,
                    123
                ],
                [
                    608,
                    97
                ],
                [
                    700,
                    71
                ],
                [
                    771,
                    57
                ],
                [
                    843,
                    51
                ],
                [
                    916,
                    49
                ]
            ]
        },
        {
            "label": "1",
            "line_color": null,
            "fill_color": null,
            "points": [
                [
                    109,
                    1239
                ],
                [
                    110,
                    1266
                ],
                [
                    377,
                    1265
                ],
                [
                    377,
                    1239
                ]
            ]
        },
        {
            "label": "1",
            "line_color": null,
            "fill_color": null,
            "points": [
                [
                    495,
                    214
                ],
                [
                    525,
                    260
                ],
                [
                    577,
                    232
                ],
                [
                    622,
                    213
                ],
                [
                    621,
                    202
                ],
                [
                    633,
                    195
                ],
                [
                    641,
                    190
                ],
                [
                    650,
                    180
                ],
                [
                    655,
                    165
                ],
                [
                    664,
                    165
                ],
                [
                    676,
                    160
                ],
                [
                    686,
                    164
                ],
                [
                    693,
                    166
                ],
                [
                    699,
                    180
                ],
                [
                    708,
                    175
                ],
                [
                    714,
                    184
                ],
                [
                    779,
                    170
                ],
                [
                    849,
                    161
                ],
                [
                    1004,
                    161
                ],
                [
                    1528,
                    160
                ],
                [
                    1527,
                    147
                ],
                [
                    1531,
                    136
                ],
                [
                    1540,
                    141
                ],
                [
                    1546,
                    145
                ],
                [
                    1552,
                    143
                ],
                [
                    1555,
                    137
                ],
                [
                    1553,
                    104
                ],
                [
                    965,
                    106
                ],
                [
                    843,
                    109
                ],
                [
                    765,
                    118
                ],
                [
                    690,
                    133
                ],
                [
                    615,
                    155
                ]
            ]
        },
        {
            "label": "1",
            "line_color": null,
            "fill_color": null,
            "points": [
                [
                    1393,
                    562
                ],
                [
                    1393,
                    591
                ],
                [
                    1396,
                    601
                ],
                [
                    1409,
                    609
                ],
                [
                    1419,
                    608
                ],
                [
                    1419,
                    562
                ]
            ]
        },
        {
            "label": "1",
            "line_color": null,
            "fill_color": null,
            "points": [
                [
                    791,
                    582
                ],
                [
                    808,
                    631
                ],
                [
                    834,
                    624
                ],
                [
                    858,
                    620
                ],
                [
                    888,
                    617
                ],
                [
                    956,
                    618
                ],
                [
                    955,
                    586
                ],
                [
                    951,
                    581
                ],
                [
                    949,
                    571
                ],
                [
                    956,
                    566
                ],
                [
                    877,
                    565
                ],
                [
                    822,
                    573
                ]
            ]
        },
        {
            "label": "1",
            "line_color": null,
            "fill_color": null,
            "points": [
                [
                    982,
                    563
                ],
                [
                    983,
                    618
                ],
                [
                    1133,
                    617
                ],
                [
                    1133,
                    563
                ]
            ]
        },
        {
            "label": "1",
            "line_color": null,
            "fill_color": null,
            "points": [
                [
                    1159,
                    563
                ],
                [
                    1160,
                    618
                ],
                [
                    1314,
                    617
                ],
                [
                    1326,
                    611
                ],
                [
                    1333,
                    603
                ],
                [
                    1341,
                    594
                ],
                [
                    1353,
                    590
                ],
                [
                    1361,
                    591
                ],
                [
                    1367,
                    582
                ],
                [
                    1372,
                    582
                ],
                [
                    1373,
                    564
                ]
            ]
        },
        {
            "label": "1",
            "line_color": null,
            "fill_color": null,
            "points": [
                [
                    745,
                    368
                ],
                [
                    756,
                    407
                ],
                [
                    713,
                    421
                ],
                [
                    678,
                    439
                ],
                [
                    667,
                    444
                ],
                [
                    660,
                    428
                ],
                [
                    654,
                    404
                ]
            ]
        },
        {
            "label": "1",
            "line_color": null,
            "fill_color": null,
            "points": [
                [
                    584,
                    626
                ],
                [
                    600,
                    606
                ],
                [
                    449,
                    470
                ],
                [
                    349,
                    383
                ],
                [
                    335,
                    386
                ],
                [
                    324,
                    382
                ],
                [
                    318,
                    377
                ],
                [
                    312,
                    382
                ],
                [
                    335,
                    407
                ]
            ]
        },
        {
            "label": "1",
            "line_color": null,
            "fill_color": null,
            "points": [
                [
                    202,
                    395
                ],
                [
                    220,
                    370
                ],
                [
                    237,
                    350
                ],
                [
                    251,
                    331
                ],
                [
                    248,
                    316
                ],
                [
                    240,
                    312
                ],
                [
                    235,
                    305
                ],
                [
                    235,
                    291
                ],
                [
                    233,
                    285
                ],
                [
                    209,
                    305
                ],
                [
                    182,
                    333
                ],
                [
                    181,
                    338
                ],
                [
                    187,
                    341
                ],
                [
                    189,
                    348
                ],
                [
                    190,
                    354
                ],
                [
                    200,
                    359
                ],
                [
                    202,
                    366
                ],
                [
                    197,
                    375
                ],
                [
                    192,
                    380
                ],
                [
                    188,
                    385
                ]
            ]
        },
        {
            "label": "1",
            "line_color": null,
            "fill_color": null,
            "points": [
                [
                    250,
                    447
                ],
                [
                    291,
                    480
                ],
                [
                    271,
                    514
                ],
                [
                    244,
                    563
                ],
                [
                    215,
                    629
                ],
                [
                    190,
                    706
                ],
                [
                    173,
                    800
                ],
                [
                    168,
                    875
                ],
                [
                    169,
                    996
                ],
                [
                    169,
                    1131
                ],
                [
                    159,
                    1125
                ],
                [
                    150,
                    1117
                ],
                [
                    140,
                    1120
                ],
                [
                    139,
                    1127
                ],
                [
                    136,
                    1131
                ],
                [
                    124,
                    1135
                ],
                [
                    114,
                    1135
                ],
                [
                    114,
                    910
                ],
                [
                    119,
                    771
                ],
                [
                    142,
                    675
                ],
                [
                    165,
                    605
                ],
                [
                    194,
                    538
                ],
                [
                    230,
                    472
                ]
            ]
        },
        {
            "label": "1",
            "line_color": null,
            "fill_color": null,
            "points": [
                [
                    351,
                    602
                ],
                [
                    304,
                    579
                ],
                [
                    291,
                    605
                ],
                [
                    272,
                    650
                ],
                [
                    256,
                    697
                ],
                [
                    241,
                    757
                ],
                [
                    232,
                    819
                ],
                [
                    230,
                    872
                ],
                [
                    230,
                    1019
                ],
                [
                    230,
                    1147
                ],
                [
                    282,
                    1148
                ],
                [
                    279,
                    1030
                ],
                [
                    279,
                    889
                ],
                [
                    284,
                    802
                ],
                [
                    299,
                    757
                ],
                [
                    317,
                    689
                ]
            ]
        },
        {
            "label": "1",
            "line_color": null,
            "fill_color": null,
            "points": [
                [
                    558,
                    704
                ],
                [
                    510,
                    680
                ],
                [
                    498,
                    703
                ],
                [
                    478,
                    751
                ],
                [
                    463,
                    808
                ],
                [
                    457,
                    867
                ],
                [
                    458,
                    948
                ],
                [
                    458,
                    1054
                ],
                [
                    458,
                    1137
                ],
                [
                    464,
                    1136
                ],
                [
                    474,
                    1143
                ],
                [
                    482,
                    1140
                ],
                [
                    493,
                    1141
                ],
                [
                    500,
                    1146
                ],
                [
                    508,
                    1150
                ],
                [
                    512,
                    1150
                ],
                [
                    514,
                    918
                ],
                [
                    516,
                    831
                ],
                [
                    531,
                    767
                ]
            ]
        },
        {
            "label": "1",
            "line_color": null,
            "fill_color": null,
            "points": [
                [
                    419,
                    607
                ],
                [
                    464,
                    633
                ],
                [
                    452,
                    660
                ],
                [
                    434,
                    699
                ],
                [
                    412,
                    760
                ],
                [
                    400,
                    828
                ],
                [
                    396,
                    893
                ],
                [
                    397,
                    1031
                ],
                [
                    397,
                    1125
                ],
                [
                    389,
                    1124
                ],
                [
                    377,
                    1115
                ],
                [
                    368,
                    1110
                ],
                [
                    361,
                    1110
                ],
                [
                    358,
                    1114
                ],
                [
                    350,
                    1118
                ],
                [
                    344,
                    1117
                ],
                [
                    344,
                    1026
                ],
                [
                    346,
                    891
                ],
                [
                    347,
                    817
                ],
                [
                    360,
                    745
                ],
                [
                    384,
                    676
                ]
            ]
        },
        {
            "label": "1",
            "line_color": null,
            "fill_color": null,
            "points": [
                [
                    184,
                    432
                ],
                [
                    157,
                    412
                ],
                [
                    150,
                    417
                ],
                [
                    141,
                    417
                ],
                [
                    139,
                    428
                ],
                [
                    138,
                    436
                ],
                [
                    130,
                    438
                ],
                [
                    120,
                    434
                ],
                [
                    116,
                    431
                ],
                [
                    97,
                    475
                ],
                [
                    97,
                    487
                ],
                [
                    91,
                    506
                ],
                [
                    84,
                    519
                ],
                [
                    77,
                    529
                ],
                [
                    71,
                    536
                ],
                [
                    55,
                    577
                ],
                [
                    32,
                    653
                ],
                [
                    16,
                    724
                ],
                [
                    7,
                    790
                ],
                [
                    3,
                    832
                ],
                [
                    16,
                    831
                ],
                [
                    28,
                    831
                ],
                [
                    38,
                    831
                ],
                [
                    46,
                    834
                ],
                [
                    58,
                    845
                ],
                [
                    68,
                    774
                ],
                [
                    88,
                    662
                ],
                [
                    106,
                    596
                ],
                [
                    121,
                    552
                ],
                [
                    149,
                    491
                ],
                [
                    170,
                    448
                ]
            ]
        },
        {
            "label": "1",
            "line_color": null,
            "fill_color": null,
            "points": [
                [
                    56,
                    1264
                ],
                [
                    3,
                    1263
                ],
                [
                    3,
                    1144
                ],
                [
                    12,
                    1133
                ],
                [
                    21,
                    1125
                ],
                [
                    29,
                    1121
                ],
                [
                    32,
                    1113
                ],
                [
                    35,
                    1110
                ],
                [
                    44,
                    1104
                ],
                [
                    52,
                    1100
                ],
                [
                    56,
                    1101
                ],
                [
                    56,
                    1246
                ]
            ]
        }
    ],
    "lineColor": [
        0,
        255,
        0,
        128
    ],
    "fillColor": [
        255,
        0,
        0,
        128
    ]
}