{
    "shapes": [
        {
            "label": "1",
            "line_color": null,
            "fill_color": null,
            "points": [
                [
                    59,
                    66
                ],
                [
                    59,
                    13
                ],
                [
                    364,
                    5
                ],
                [
                    367,
                    57
                ]
            ]
        },
        {
            "label": "1",
            "line_color": null,
            "fill_color": null,
            "points": [
                [
                    126,
                    118
                ],
                [
                    127,
                    173
                ],
                [
                    371,
                    168
                ],
                [
                    370,
                    111
                ]
            ]
        },
        {
            "label": "1",
            "line_color": null,
            "fill_color": null,
            "points": [
                [
                    131,
                    281
                ],
                [
                    130,
                    227
                ],
                [
                    373,
                    223
                ],
                [
                    375,
                    275
                ]
            ]
        },
        {
            "label": "1",
            "line_color": null,
            "fill_color": null,
            "points": [
                [
                    442,
                    0
                ],
                [
                    496.0,
                    0.0
                ],
                [
                    510,
                    429
                ],
                [
                    456,
                    431
                ],
                [
                    448,
                    228
                ]
            ]
        },
        {
            "label": "1",
            "line_color": null,
            "fill_color": null,
            "points": [
                [
                    405,
                    113
                ],
                [
                    411,
                    275
                ],
                [
                    385,
                    275
                ],
                [
                    380,
                    114
                ]
            ]
        },
        {
            "label": "1",
            "line_color": null,
            "fill_color": null,
            "points": [
                [
                    54,
                    79
                ],
                [
                    2,
                    80
                ],
                [
                    0.0,
                    82.0
                ],
                [
                    7,
                    357
                ],
                [
                    60,
                    350
                ]
            ]
        },
        {
            "label": "1",
            "line_color": null,
            "fill_color": null,
            "points": [
                [
                    159,
                    335
                ],
                [
                    161,
                    402
                ],
                [
                    63,
                    410
                ],
                [
                    60,
                    337
                ]
            ]
        },
        {
            "label": "1",
            "line_color": null,
            "fill_color": null,
            "points": [
                [
                    234,
                    373
                ],
                [
                    235,
                    429
                ],
                [
                    390,
                    427
                ],
                [
                    389,
                    368
                ]
            ]
        },
        {
            "label": "1",
            "line_color": null,
            "fill_color": null,
            "points": [
                [
                    318,
                    498
                ],
                [
                    305,
                    444
                ],
                [
                    226,
                    446
                ],
                [
                    225,
                    499
                ]
            ]
        },
        {
            "label": "1",
            "line_color": null,
            "fill_color": null,
            "points": [
                [
                    177,
                    495
                ],
                [
                    170,
                    444
                ],
                [
                    116,
                    452
                ],
                [
                    58,
                    475
                ],
                [
                    28,
                    492
                ],
                [
                    42,
                    513
                ],
                [
                    107,
                    513
                ]
            ]
        }
    ],
    "lineColor": [
        0,
        255,
        0,
        128
    ],
    "fillColor": [
        255,
        0,
        0,
        128
    ]
}