{
    "shapes": [
        {
            "line_color": null,
            "points": [
                [
                    33.40909090909092,
                    34.681818181818194
                ],
                [
                    29.40909090909092,
                    0.6818181818181923
                ],
                [
                    50.40909090909092,
                    0.6818181818181923
                ],
                [
                    220.40909090909093,
                    25.681818181818194
                ],
                [
                    229.40909090909093,
                    63.681818181818194
                ],
                [
                    228.40909090909093,
                    67.68181818181819
                ]
            ],
            "fill_color": null,
            "label": "1"
        },
        {
            "line_color": null,
            "points": [
                [
                    17.40909090909092,
                    132.6818181818182
                ],
                [
                    164.40909090909093,
                    156.6818181818182
                ],
                [
                    157.40909090909093,
                    197.6818181818182
                ],
                [
                    3.4090909090909207,
                    171.6818181818182
                ],
                [
                    7.409090909090921,
                    138.6818181818182
                ]
            ],
            "fill_color": null,
            "label": "1"
        },
        {
            "line_color": null,
            "points": [
                [
                    277.40909090909093,
                    204.6818181818182
                ],
                [
                    237.40909090909093,
                    195.6818181818182
                ],
                [
                    253.40909090909093,
                    68.68181818181819
                ],
                [
                    278.0,
                    71.63272727272728
                ]
            ],
            "fill_color": null,
            "label": "1"
        }
    ],
    "imagePath": "C:/Users/langh/Dropbox/MCC-I Masters/Thesis/A6/dataset/images/508801197.json",
    "fillColor": [
        255,
        0,
        0,
        128
    ]
}