{
    "shapes": [
        {
            "line_color": null,
            "points": [
                [
                    133.0,
                    45.0
                ],
                [
                    154.0,
                    43.0
                ],
                [
                    172.0,
                    228.0
                ],
                [
                    150.0,
                    229.0
                ]
            ],
            "fill_color": null,
            "label": "1"
        },
        {
            "line_color": null,
            "points": [
                [
                    102.0,
                    28.0
                ],
                [
                    112.0,
                    126.0
                ],
                [
                    93.0,
                    126.0
                ],
                [
                    84.0,
                    16.0
                ],
                [
                    100.0,
                    13.0
                ]
            ],
            "fill_color": null,
            "label": "1"
        },
        {
            "line_color": null,
            "points": [
                [
                    113.0,
                    355.0
                ],
                [
                    79.0,
                    353.0
                ],
                [
                    117.0,
                    730.0
                ],
                [
                    156.0,
                    732.0
                ]
            ],
            "fill_color": null,
            "label": "1"
        },
        {
            "line_color": null,
            "points": [
                [
                    44.0,
                    390.0
                ],
                [
                    82.0,
                    390.0
                ],
                [
                    120.0,
                    727.0
                ],
                [
                    134.0,
                    728.0
                ],
                [
                    135.0,
                    747.0
                ],
                [
                    103.0,
                    746.0
                ],
                [
                    84.0,
                    727.0
                ]
            ],
            "fill_color": null,
            "label": "1"
        },
        {
            "line_color": null,
            "points": [
                [
                    164.0,
                    539.0
                ],
                [
                    215.0,
                    529.0
                ],
                [
                    222.0,
                    602.0
                ],
                [
                    175.0,
                    615.0
                ]
            ],
            "fill_color": null,
            "label": "1"
        }
    ],
    "imagePath": "C:/Users/langh/Dropbox/MCC-I Masters/Thesis/A6/dataset/images/156360956.json",
    "fillColor": [
        255,
        0,
        0,
        128
    ]
}