{
    "shapes": [
        {
            "label": "1",
            "line_color": null,
            "fill_color": null,
            "points": [
                [
                    85,
                    211
                ],
                [
                    126,
                    208
                ],
                [
                    151,
                    428
                ],
                [
                    108,
                    436
                ]
            ]
        },
        {
            "label": "1",
            "line_color": null,
            "fill_color": null,
            "points": [
                [
                    172,
                    203
                ],
                [
                    133,
                    209
                ],
                [
                    151,
                    430
                ],
                [
                    194,
                    428
                ]
            ]
        },
        {
            "label": "1",
            "line_color": null,
            "fill_color": null,
            "points": [
                [
                    210,
                    199
                ],
                [
                    251,
                    196
                ],
                [
                    275,
                    417
                ],
                [
                    234,
                    423
                ]
            ]
        },
        {
            "label": "1",
            "line_color": null,
            "fill_color": null,
            "points": [
                [
                    295,
                    190
                ],
                [
                    256,
                    194
                ],
                [
                    278,
                    418
                ],
                [
                    319,
                    414
                ]
            ]
        },
        {
            "label": "1",
            "line_color": null,
            "fill_color": null,
            "points": [
                [
                    334,
                    187
                ],
                [
                    373,
                    184
                ],
                [
                    396,
                    405
                ],
                [
                    358,
                    410
                ],
                [
                    355,
                    409
                ]
            ]
        },
        {
            "label": "1",
            "line_color": null,
            "fill_color": null,
            "points": [
                [
                    419,
                    179
                ],
                [
                    379,
                    183
                ],
                [
                    401,
                    405
                ],
                [
                    441,
                    402
                ]
            ]
        },
        {
            "label": "1",
            "line_color": null,
            "fill_color": null,
            "points": [
                [
                    31,
                    163
                ],
                [
                    27,
                    121
                ],
                [
                    487,
                    74
                ],
                [
                    491,
                    116
                ]
            ]
        },
        {
            "label": "1",
            "line_color": null,
            "fill_color": null,
            "points": [
                [
                    529,
                    111
                ],
                [
                    525,
                    70
                ],
                [
                    1123,
                    7
                ],
                [
                    1129,
                    47
                ],
                [
                    1129,
                    49
                ]
            ]
        },
        {
            "label": "1",
            "line_color": null,
            "fill_color": null,
            "points": [
                [
                    589,
                    161
                ],
                [
                    550,
                    166
                ],
                [
                    572,
                    371
                ],
                [
                    611,
                    369
                ]
            ]
        },
        {
            "label": "1",
            "line_color": null,
            "fill_color": null,
            "points": [
                [
                    457,
                    169
                ],
                [
                    499,
                    165
                ],
                [
                    517,
                    356
                ],
                [
                    476,
                    359
                ]
            ]
        },
        {
            "label": "1",
            "line_color": null,
            "fill_color": null,
            "points": [
                [
                    651,
                    379
                ],
                [
                    692,
                    375
                ],
                [
                    668,
                    154
                ],
                [
                    628,
                    157
                ]
            ]
        },
        {
            "label": "1",
            "line_color": null,
            "fill_color": null,
            "points": [
                [
                    712,
                    149
                ],
                [
                    674,
                    153
                ],
                [
                    697,
                    375
                ],
                [
                    737,
                    371
                ]
            ]
        },
        {
            "label": "1",
            "line_color": null,
            "fill_color": null,
            "points": [
                [
                    752,
                    145
                ],
                [
                    792,
                    141
                ],
                [
                    814,
                    361
                ],
                [
                    775,
                    367
                ]
            ]
        },
        {
            "label": "1",
            "line_color": null,
            "fill_color": null,
            "points": [
                [
                    838,
                    136
                ],
                [
                    798,
                    140
                ],
                [
                    821,
                    362
                ],
                [
                    860,
                    358
                ]
            ]
        },
        {
            "label": "1",
            "line_color": null,
            "fill_color": null,
            "points": [
                [
                    877,
                    132
                ],
                [
                    916,
                    128
                ],
                [
                    939,
                    348
                ],
                [
                    898,
                    354
                ]
            ]
        },
        {
            "label": "1",
            "line_color": null,
            "fill_color": null,
            "points": [
                [
                    961,
                    123
                ],
                [
                    923,
                    127
                ],
                [
                    944,
                    348
                ],
                [
                    983,
                    345
                ]
            ]
        },
        {
            "label": "1",
            "line_color": null,
            "fill_color": null,
            "points": [
                [
                    1000,
                    120
                ],
                [
                    1040,
                    115
                ],
                [
                    1062,
                    334
                ],
                [
                    1023,
                    341
                ]
            ]
        },
        {
            "label": "1",
            "line_color": null,
            "fill_color": null,
            "points": [
                [
                    1086,
                    110
                ],
                [
                    1045,
                    114
                ],
                [
                    1068,
                    335
                ],
                [
                    1109,
                    332
                ]
            ]
        }
    ],
    "lineColor": [
        0,
        255,
        0,
        128
    ],
    "fillColor": [
        255,
        0,
        0,
        128
    ]
}