{
    "shapes": [
        {
            "label": "1",
            "line_color": null,
            "fill_color": null,
            "points": [
                [
                    101,
                    20
                ],
                [
                    158,
                    360
                ],
                [
                    113,
                    367
                ],
                [
                    57,
                    25
                ]
            ]
        },
        {
            "label": "1",
            "line_color": null,
            "fill_color": null,
            "points": [
                [
                    160,
                    365
                ],
                [
                    116,
                    373
                ],
                [
                    119,
                    398
                ],
                [
                    163,
                    390
                ]
            ]
        }
    ],
    "lineColor": [
        0,
        255,
        0,
        128
    ],
    "fillColor": [
        255,
        0,
        0,
        128
    ]
}