{
    "shapes": [
        {
            "label": "1",
            "line_color": null,
            "fill_color": null,
            "points": [
                [
                    64,
                    341
                ],
                [
                    71,
                    403
                ],
                [
                    1449,
                    312
                ],
                [
                    1446,
                    255
                ]
            ]
        },
        {
            "label": "1",
            "line_color": null,
            "fill_color": null,
            "points": [
                [
                    1501,
                    359
                ],
                [
                    1495,
                    304
                ],
                [
                    71,
                    399
                ],
                [
                    74,
                    452
                ]
            ]
        },
        {
            "label": "1",
            "line_color": null,
            "fill_color": null,
            "points": [
                [
                    1551,
                    411
                ],
                [
                    1555,
                    465
                ],
                [
                    82,
                    564
                ],
                [
                    78,
                    508
                ]
            ]
        },
        {
            "label": "1",
            "line_color": null,
            "fill_color": null,
            "points": [
                [
                    1581,
                    515
                ],
                [
                    1579,
                    461
                ],
                [
                    81,
                    559
                ],
                [
                    85,
                    615
                ]
            ]
        },
        {
            "label": "1",
            "line_color": null,
            "fill_color": null,
            "points": [
                [
                    1635,
                    566
                ],
                [
                    1638,
                    624
                ],
                [
                    21,
                    729
                ],
                [
                    19,
                    675
                ]
            ]
        },
        {
            "label": "1",
            "line_color": null,
            "fill_color": null,
            "points": [
                [
                    1642,
                    674
                ],
                [
                    1639,
                    618
                ],
                [
                    24,
                    726
                ],
                [
                    26,
                    779
                ]
            ]
        },
        {
            "label": "1",
            "line_color": null,
            "fill_color": null,
            "points": [
                [
                    1670,
                    890
                ],
                [
                    1675,
                    950
                ],
                [
                    1773,
                    947
                ],
                [
                    1821,
                    942
                ],
                [
                    1818,
                    881
                ]
            ]
        },
        {
            "label": "1",
            "line_color": null,
            "fill_color": null,
            "points": [
                [
                    213,
                    280
                ],
                [
                    213,
                    227
                ],
                [
                    540,
                    209
                ],
                [
                    626,
                    200
                ],
                [
                    629,
                    255
                ]
            ]
        },
        {
            "label": "1",
            "line_color": null,
            "fill_color": null,
            "points": [
                [
                    721,
                    250
                ],
                [
                    717,
                    194
                ],
                [
                    1421,
                    149
                ],
                [
                    1424,
                    201
                ]
            ]
        },
        {
            "label": "1",
            "line_color": null,
            "fill_color": null,
            "points": [
                [
                    805,
                    79
                ],
                [
                    806,
                    29
                ],
                [
                    828,
                    28
                ],
                [
                    832,
                    78
                ]
            ]
        },
        {
            "label": "1",
            "line_color": null,
            "fill_color": null,
            "points": [
                [
                    844,
                    78
                ],
                [
                    841,
                    18
                ],
                [
                    888,
                    17
                ],
                [
                    888,
                    76
                ]
            ]
        },
        {
            "label": "1",
            "line_color": null,
            "fill_color": null,
            "points": [
                [
                    897,
                    74
                ],
                [
                    896,
                    15
                ],
                [
                    940,
                    12
                ],
                [
                    944,
                    71
                ]
            ]
        },
        {
            "label": "1",
            "line_color": null,
            "fill_color": null,
            "points": [
                [
                    953,
                    70
                ],
                [
                    951,
                    12
                ],
                [
                    996,
                    10
                ],
                [
                    1001,
                    69
                ]
            ]
        },
        {
            "label": "1",
            "line_color": null,
            "fill_color": null,
            "points": [
                [
                    1010,
                    68
                ],
                [
                    1008,
                    10
                ],
                [
                    1052,
                    8
                ],
                [
                    1057,
                    65
                ]
            ]
        },
        {
            "label": "1",
            "line_color": null,
            "fill_color": null,
            "points": [
                [
                    1067,
                    64
                ],
                [
                    1065,
                    4
                ],
                [
                    1110,
                    2
                ],
                [
                    1114,
                    60
                ]
            ]
        },
        {
            "label": "1",
            "line_color": null,
            "fill_color": null,
            "points": [
                [
                    1125,
                    60
                ],
                [
                    1121,
                    2
                ],
                [
                    1166,
                    0
                ],
                [
                    1170,
                    56
                ]
            ]
        },
        {
            "label": "1",
            "line_color": null,
            "fill_color": null,
            "points": [
                [
                    1181,
                    57
                ],
                [
                    1178,
                    1
                ],
                [
                    1202,
                    0
                ],
                [
                    1205,
                    55
                ]
            ]
        },
        {
            "label": "1",
            "line_color": null,
            "fill_color": null,
            "points": [
                [
                    1224,
                    54
                ],
                [
                    1220,
                    0
                ],
                [
                    1268,
                    0
                ],
                [
                    1271,
                    51
                ]
            ]
        },
        {
            "label": "1",
            "line_color": null,
            "fill_color": null,
            "points": [
                [
                    1288,
                    49
                ],
                [
                    1285,
                    2
                ],
                [
                    1331.0,
                    0.0
                ],
                [
                    1334,
                    47
                ]
            ]
        }
    ],
    "lineColor": [
        0,
        255,
        0,
        128
    ],
    "fillColor": [
        255,
        0,
        0,
        128
    ]
}