{
    "shapes": [
        {
            "label": "1",
            "line_color": null,
            "fill_color": null,
            "points": [
                [
                    559,
                    108
                ],
                [
                    564,
                    166
                ],
                [
                    96,
                    220
                ],
                [
                    91,
                    162
                ]
            ]
        },
        {
            "label": "1",
            "line_color": null,
            "fill_color": null,
            "points": [
                [
                    572,
                    216
                ],
                [
                    564,
                    161
                ],
                [
                    95,
                    215
                ],
                [
                    104,
                    272
                ]
            ]
        },
        {
            "label": "1",
            "line_color": null,
            "fill_color": null,
            "points": [
                [
                    264,
                    318
                ],
                [
                    271,
                    373
                ],
                [
                    62,
                    397
                ],
                [
                    55,
                    342
                ]
            ]
        },
        {
            "label": "1",
            "line_color": null,
            "fill_color": null,
            "points": [
                [
                    428,
                    301
                ],
                [
                    429,
                    317
                ],
                [
                    438,
                    356
                ],
                [
                    647,
                    334
                ],
                [
                    640,
                    277
                ]
            ]
        },
        {
            "label": "1",
            "line_color": null,
            "fill_color": null,
            "points": [
                [
                    36,
                    102
                ],
                [
                    31,
                    51
                ],
                [
                    128,
                    39
                ],
                [
                    288,
                    20
                ],
                [
                    467,
                    1
                ],
                [
                    609,
                    0
                ],
                [
                    612,
                    35
                ],
                [
                    472,
                    53
                ],
                [
                    283,
                    76
                ],
                [
                    81,
                    98
                ]
            ]
        },
        {
            "label": "1",
            "line_color": null,
            "fill_color": null,
            "points": [
                [
                    32,
                    102
                ],
                [
                    0,
                    106
                ],
                [
                    0,
                    165
                ],
                [
                    22,
                    349
                ],
                [
                    61,
                    344
                ]
            ]
        }
    ],
    "lineColor": [
        0,
        255,
        0,
        128
    ],
    "fillColor": [
        255,
        0,
        0,
        128
    ]
}