{
    "shapes": [
        {
            "label": "1",
            "line_color": null,
            "fill_color": null,
            "points": [
                [
                    322,
                    232
                ],
                [
                    348,
                    272
                ],
                [
                    214,
                    368
                ],
                [
                    203,
                    368
                ],
                [
                    178,
                    338
                ]
            ]
        },
        {
            "label": "1",
            "line_color": null,
            "fill_color": null,
            "points": [
                [
                    289,
                    190
                ],
                [
                    260,
                    148
                ],
                [
                    134,
                    238
                ],
                [
                    161,
                    282
                ]
            ]
        },
        {
            "label": "1",
            "line_color": null,
            "fill_color": null,
            "points": [
                [
                    192,
                    103
                ],
                [
                    227,
                    139
                ],
                [
                    120,
                    250
                ],
                [
                    83,
                    216
                ]
            ]
        },
        {
            "label": "1",
            "line_color": null,
            "fill_color": null,
            "points": [
                [
                    205,
                    46
                ],
                [
                    193,
                    5
                ],
                [
                    205,
                    1
                ],
                [
                    219,
                    0
                ],
                [
                    234,
                    36
                ]
            ]
        },
        {
            "label": "1",
            "line_color": null,
            "fill_color": null,
            "points": [
                [
                    189,
                    53
                ],
                [
                    174,
                    12
                ],
                [
                    148,
                    22
                ],
                [
                    118,
                    31
                ],
                [
                    6,
                    149
                ],
                [
                    39,
                    184
                ],
                [
                    142,
                    77
                ],
                [
                    152,
                    68
                ]
            ]
        },
        {
            "label": "1",
            "line_color": null,
            "fill_color": null,
            "points": [
                [
                    42.0,
                    0.0
                ],
                [
                    0,
                    43
                ],
                [
                    0.0,
                    118.0
                ],
                [
                    87,
                    29
                ],
                [
                    103,
                    13
                ],
                [
                    87,
                    0
                ]
            ]
        }
    ],
    "lineColor": [
        0,
        255,
        0,
        128
    ],
    "fillColor": [
        255,
        0,
        0,
        128
    ]
}