{
    "shapes": [
        {
            "label": "1",
            "line_color": null,
            "fill_color": null,
            "points": [
                [
                    163,
                    83
                ],
                [
                    117,
                    69
                ],
                [
                    136,
                    7
                ],
                [
                    182,
                    22
                ]
            ]
        },
        {
            "label": "1",
            "line_color": null,
            "fill_color": null,
            "points": [
                [
                    202,
                    77
                ],
                [
                    218,
                    32
                ],
                [
                    427,
                    89
                ],
                [
                    467,
                    104
                ],
                [
                    518,
                    122
                ],
                [
                    504,
                    167
                ]
            ]
        },
        {
            "label": "1",
            "line_color": null,
            "fill_color": null,
            "points": [
                [
                    199,
                    115
                ],
                [
                    247,
                    131
                ],
                [
                    226,
                    196
                ],
                [
                    192,
                    186
                ],
                [
                    181,
                    177
                ]
            ]
        },
        {
            "label": "1",
            "line_color": null,
            "fill_color": null,
            "points": [
                [
                    284,
                    139
                ],
                [
                    328,
                    157
                ],
                [
                    297,
                    239
                ],
                [
                    259,
                    223
                ],
                [
                    255,
                    217
                ]
            ]
        },
        {
            "label": "1",
            "line_color": null,
            "fill_color": null,
            "points": [
                [
                    367,
                    171
                ],
                [
                    325,
                    157
                ],
                [
                    293,
                    237
                ],
                [
                    336,
                    255
                ]
            ]
        },
        {
            "label": "1",
            "line_color": null,
            "fill_color": null,
            "points": [
                [
                    404,
                    178
                ],
                [
                    446,
                    196
                ],
                [
                    415,
                    276
                ],
                [
                    371,
                    260
                ]
            ]
        },
        {
            "label": "1",
            "line_color": null,
            "fill_color": null,
            "points": [
                [
                    448,
                    306
                ],
                [
                    468,
                    262
                ],
                [
                    581,
                    315
                ],
                [
                    598,
                    333
                ],
                [
                    580,
                    372
                ]
            ]
        },
        {
            "label": "1",
            "line_color": null,
            "fill_color": null,
            "points": [
                [
                    366,
                    267
                ],
                [
                    412,
                    276
                ],
                [
                    377,
                    476
                ],
                [
                    334,
                    466
                ]
            ]
        },
        {
            "label": "1",
            "line_color": null,
            "fill_color": null,
            "points": [
                [
                    593,
                    375
                ],
                [
                    596,
                    329
                ],
                [
                    621,
                    329
                ],
                [
                    797,
                    343
                ],
                [
                    794,
                    392
                ]
            ]
        },
        {
            "label": "1",
            "line_color": null,
            "fill_color": null,
            "points": [
                [
                    738,
                    425
                ],
                [
                    736,
                    472
                ],
                [
                    424,
                    451
                ],
                [
                    428,
                    404
                ]
            ]
        },
        {
            "label": "1",
            "line_color": null,
            "fill_color": null,
            "points": [
                [
                    733,
                    514
                ],
                [
                    736,
                    469
                ],
                [
                    425,
                    448
                ],
                [
                    423,
                    493
                ]
            ]
        },
        {
            "label": "1",
            "line_color": null,
            "fill_color": null,
            "points": [
                [
                    837,
                    393
                ],
                [
                    799,
                    389
                ],
                [
                    791,
                    386
                ],
                [
                    795,
                    345
                ],
                [
                    803,
                    342
                ],
                [
                    809,
                    338
                ],
                [
                    808,
                    332
                ],
                [
                    804,
                    328
                ],
                [
                    808,
                    320
                ],
                [
                    813,
                    317
                ],
                [
                    822,
                    306
                ],
                [
                    831,
                    295
                ],
                [
                    832,
                    288
                ],
                [
                    852,
                    292
                ]
            ]
        },
        {
            "label": "1",
            "line_color": null,
            "fill_color": null,
            "points": [
                [
                    887,
                    296
                ],
                [
                    933,
                    304
                ],
                [
                    918,
                    406
                ],
                [
                    872,
                    398
                ]
            ]
        },
        {
            "label": "1",
            "line_color": null,
            "fill_color": null,
            "points": [
                [
                    975,
                    309
                ],
                [
                    930,
                    303
                ],
                [
                    915,
                    405
                ],
                [
                    962,
                    412
                ]
            ]
        },
        {
            "label": "1",
            "line_color": null,
            "fill_color": null,
            "points": [
                [
                    1009,
                    315
                ],
                [
                    1050,
                    319
                ],
                [
                    1043,
                    382
                ],
                [
                    1044,
                    391
                ],
                [
                    1039,
                    424
                ],
                [
                    993,
                    416
                ]
            ]
        },
        {
            "label": "1",
            "line_color": null,
            "fill_color": null,
            "points": [
                [
                    1121,
                    399
                ],
                [
                    1115,
                    445
                ],
                [
                    1036,
                    433
                ],
                [
                    1042,
                    388
                ],
                [
                    1048,
                    382
                ],
                [
                    1112,
                    392
                ]
            ]
        },
        {
            "label": "1",
            "line_color": null,
            "fill_color": null,
            "points": [
                [
                    229,
                    438
                ],
                [
                    232,
                    396
                ],
                [
                    250,
                    393
                ],
                [
                    280,
                    393
                ],
                [
                    331,
                    396
                ],
                [
                    339,
                    405
                ],
                [
                    337,
                    444
                ]
            ]
        },
        {
            "label": "1",
            "line_color": null,
            "fill_color": null,
            "points": [
                [
                    370,
                    512
                ],
                [
                    362,
                    558
                ],
                [
                    102,
                    515
                ],
                [
                    109,
                    472
                ],
                [
                    132,
                    475
                ],
                [
                    163,
                    481
                ],
                [
                    169,
                    491
                ],
                [
                    179,
                    499
                ],
                [
                    187,
                    500
                ],
                [
                    197,
                    500
                ],
                [
                    205,
                    499
                ],
                [
                    212,
                    495
                ],
                [
                    219,
                    491
                ],
                [
                    223,
                    486
                ]
            ]
        },
        {
            "label": "1",
            "line_color": null,
            "fill_color": null,
            "points": [
                [
                    369,
                    597
                ],
                [
                    361,
                    643
                ],
                [
                    102,
                    599
                ],
                [
                    111,
                    551
                ]
            ]
        },
        {
            "label": "1",
            "line_color": null,
            "fill_color": null,
            "points": [
                [
                    352,
                    687
                ],
                [
                    361,
                    641
                ],
                [
                    102,
                    596
                ],
                [
                    95,
                    642
                ]
            ]
        },
        {
            "label": "1",
            "line_color": null,
            "fill_color": null,
            "points": [
                [
                    709,
                    550
                ],
                [
                    706,
                    597
                ],
                [
                    438,
                    578
                ],
                [
                    442,
                    531
                ]
            ]
        },
        {
            "label": "1",
            "line_color": null,
            "fill_color": null,
            "points": [
                [
                    704,
                    637
                ],
                [
                    707,
                    593
                ],
                [
                    438,
                    574
                ],
                [
                    434,
                    620
                ],
                [
                    682,
                    638
                ]
            ]
        },
        {
            "label": "1",
            "line_color": null,
            "fill_color": null,
            "points": [
                [
                    130,
                    937
                ],
                [
                    181,
                    920
                ],
                [
                    102,
                    669
                ],
                [
                    52,
                    688
                ]
            ]
        },
        {
            "label": "1",
            "line_color": null,
            "fill_color": null,
            "points": [
                [
                    207,
                    714
                ],
                [
                    252,
                    710
                ],
                [
                    273,
                    891
                ],
                [
                    228,
                    896
                ]
            ]
        },
        {
            "label": "1",
            "line_color": null,
            "fill_color": null,
            "points": [
                [
                    296,
                    724
                ],
                [
                    250,
                    729
                ],
                [
                    270,
                    892
                ],
                [
                    317,
                    887
                ]
            ]
        },
        {
            "label": "1",
            "line_color": null,
            "fill_color": null,
            "points": [
                [
                    339,
                    727
                ],
                [
                    385,
                    721
                ],
                [
                    405,
                    884
                ],
                [
                    359,
                    889
                ]
            ]
        },
        {
            "label": "1",
            "line_color": null,
            "fill_color": null,
            "points": [
                [
                    432,
                    719
                ],
                [
                    383,
                    722
                ],
                [
                    405,
                    904
                ],
                [
                    450,
                    898
                ]
            ]
        },
        {
            "label": "1",
            "line_color": null,
            "fill_color": null,
            "points": [
                [
                    687,
                    675
                ],
                [
                    685,
                    722
                ],
                [
                    516,
                    710
                ],
                [
                    520,
                    664
                ]
            ]
        },
        {
            "label": "1",
            "line_color": null,
            "fill_color": null,
            "points": [
                [
                    467,
                    689
                ],
                [
                    514,
                    683
                ],
                [
                    519,
                    730
                ],
                [
                    543,
                    942
                ],
                [
                    544,
                    962
                ],
                [
                    541,
                    977
                ],
                [
                    494,
                    969
                ],
                [
                    499,
                    947
                ],
                [
                    491,
                    881
                ]
            ]
        },
        {
            "label": "1",
            "line_color": null,
            "fill_color": null,
            "points": [
                [
                    266,
                    946
                ],
                [
                    257,
                    995
                ],
                [
                    173,
                    984
                ],
                [
                    182,
                    936
                ]
            ]
        },
        {
            "label": "1",
            "line_color": null,
            "fill_color": null,
            "points": [
                [
                    294,
                    950
                ],
                [
                    286,
                    999
                ],
                [
                    264,
                    996
                ],
                [
                    270,
                    949
                ]
            ]
        },
        {
            "label": "1",
            "line_color": null,
            "fill_color": null,
            "points": [
                [
                    781,
                    450
                ],
                [
                    824,
                    458
                ],
                [
                    821,
                    489
                ],
                [
                    817,
                    501
                ],
                [
                    775,
                    737
                ],
                [
                    728,
                    730
                ]
            ]
        },
        {
            "label": "1",
            "line_color": null,
            "fill_color": null,
            "points": [
                [
                    826,
                    445
                ],
                [
                    823,
                    486
                ],
                [
                    828,
                    491
                ],
                [
                    854,
                    495
                ],
                [
                    1128,
                    529
                ],
                [
                    1134,
                    484
                ]
            ]
        },
        {
            "label": "1",
            "line_color": null,
            "fill_color": null,
            "points": [
                [
                    924,
                    829
                ],
                [
                    969,
                    834
                ],
                [
                    963,
                    1030
                ],
                [
                    952,
                    1033
                ],
                [
                    918,
                    1030
                ]
            ]
        },
        {
            "label": "1",
            "line_color": null,
            "fill_color": null,
            "points": [
                [
                    846,
                    858
                ],
                [
                    887,
                    861
                ],
                [
                    877,
                    1006
                ],
                [
                    830,
                    1000
                ]
            ]
        }
    ],
    "lineColor": [
        0,
        255,
        0,
        128
    ],
    "fillColor": [
        255,
        0,
        0,
        128
    ]
}