{
    "shapes": [
        {
            "label": "1",
            "line_color": null,
            "fill_color": null,
            "points": [
                [
                    361,
                    61
                ],
                [
                    315,
                    12
                ],
                [
                    232,
                    22
                ],
                [
                    224,
                    29
                ],
                [
                    215,
                    34
                ],
                [
                    203,
                    38
                ],
                [
                    185,
                    46
                ],
                [
                    178,
                    48
                ],
                [
                    173,
                    36
                ],
                [
                    168,
                    31
                ],
                [
                    144,
                    35
                ],
                [
                    137,
                    36
                ],
                [
                    129,
                    44
                ],
                [
                    121,
                    49
                ],
                [
                    97,
                    42
                ],
                [
                    91,
                    38
                ],
                [
                    75,
                    43
                ],
                [
                    42,
                    49
                ],
                [
                    23,
                    69
                ],
                [
                    60,
                    106
                ],
                [
                    95,
                    101
                ]
            ]
        },
        {
            "label": "1",
            "line_color": null,
            "fill_color": null,
            "points": [
                [
                    65,
                    102
                ],
                [
                    11,
                    107
                ],
                [
                    28,
                    253
                ],
                [
                    84,
                    245
                ]
            ]
        },
        {
            "label": "1",
            "line_color": null,
            "fill_color": null,
            "points": [
                [
                    28,
                    271
                ],
                [
                    84,
                    252
                ],
                [
                    87,
                    290
                ],
                [
                    33,
                    298
                ]
            ]
        }
    ],
    "lineColor": [
        0,
        255,
        0,
        128
    ],
    "fillColor": [
        255,
        0,
        0,
        128
    ]
}