{
    "shapes": [
        {
            "label": "1",
            "line_color": null,
            "fill_color": null,
            "points": [
                [
                    57,
                    47
                ],
                [
                    68,
                    1
                ],
                [
                    116,
                    10
                ],
                [
                    207,
                    31
                ],
                [
                    281,
                    59
                ],
                [
                    339,
                    100
                ],
                [
                    373,
                    137
                ],
                [
                    353,
                    202
                ],
                [
                    333,
                    172
                ],
                [
                    299,
                    136
                ],
                [
                    264,
                    110
                ],
                [
                    225,
                    93
                ],
                [
                    162,
                    73
                ]
            ]
        },
        {
            "label": "1",
            "line_color": null,
            "fill_color": null,
            "points": [
                [
                    348,
                    198
                ],
                [
                    397,
                    173
                ],
                [
                    464,
                    306
                ],
                [
                    550,
                    483
                ],
                [
                    505,
                    510
                ],
                [
                    474,
                    448
                ],
                [
                    369,
                    232
                ]
            ]
        },
        {
            "label": "1",
            "line_color": null,
            "fill_color": null,
            "points": [
                [
                    146,
                    156
                ],
                [
                    194,
                    132
                ],
                [
                    420,
                    578
                ],
                [
                    372,
                    603
                ]
            ]
        },
        {
            "label": "1",
            "line_color": null,
            "fill_color": null,
            "points": [
                [
                    277,
                    186
                ],
                [
                    230,
                    211
                ],
                [
                    399,
                    543
                ],
                [
                    446,
                    518
                ]
            ]
        },
        {
            "label": "1",
            "line_color": null,
            "fill_color": null,
            "points": [
                [
                    254,
                    488
                ],
                [
                    232,
                    500
                ],
                [
                    234,
                    510
                ],
                [
                    240,
                    514
                ],
                [
                    246,
                    520
                ],
                [
                    251,
                    529
                ],
                [
                    251,
                    537
                ],
                [
                    246,
                    546
                ],
                [
                    252,
                    561
                ],
                [
                    258,
                    567
                ],
                [
                    286,
                    552
                ]
            ]
        },
        {
            "label": "1",
            "line_color": null,
            "fill_color": null,
            "points": [
                [
                    470,
                    574
                ],
                [
                    514,
                    597
                ],
                [
                    499,
                    629
                ],
                [
                    485,
                    661
                ],
                [
                    473,
                    665
                ],
                [
                    466,
                    674
                ],
                [
                    464,
                    678
                ],
                [
                    468,
                    686
                ],
                [
                    467,
                    695
                ],
                [
                    463,
                    705
                ],
                [
                    458,
                    717
                ],
                [
                    414,
                    698
                ]
            ]
        }
    ],
    "lineColor": [
        0,
        255,
        0,
        128
    ],
    "fillColor": [
        255,
        0,
        0,
        128
    ]
}